subtitle_filter/__init__.py
subtitle_filter/libs/__init__.py
subtitle_filter/libs/subtitle.py
subtitle_filter-1.5.0.data/scripts/filter-subtitles.py
subtitle_filter-1.5.0.dist-info/LICENSE
subtitle_filter-1.5.0.dist-info/METADATA
subtitle_filter-1.5.0.dist-info/WHEEL
subtitle_filter-1.5.0.dist-info/top_level.txt
subtitle_filter-1.5.0.dist-info/RECORD
