Metadata-Version: 2.1
Name: subtitle-filter
Version: 1.5.0
Summary: Filter SDH entries and more from .srt files
Home-page: https://github.com/mattlyon93/filter-subs
Download-URL: https://github.com/mattlyon93/filter-subs/archive/v1.5.0.tar.gz
Author: Matt Lyon
Author-email: matthewlyon18@gmail.com
License: MIT License
Keywords: subtitle,SDH,hard-of-hearing,filter,movie,tv
Classifier: Programming Language :: Python
Classifier: Operating System :: Unix
Classifier: Operating System :: MacOS
Classifier: Topic :: Text Processing :: Filters
Classifier: Topic :: Multimedia :: Sound/Audio :: Speech
Requires-Python: >=3.5
License-File: LICENSE
